{
  "animateLoading": true,
  "borderRadius": "{{appsmith.theme.borderRadius.appBorderRadius}}",
  "bottomRow": 4,
  "boxShadow": "none",
  "buttonColor": "{{appsmith.theme.colors.backgroundColor}}",
  "buttonVariant": "PRIMARY",
  "disabledWhenInvalid": false,
  "dynamicBindingPathList": [
    {
      "key": "buttonColor"
    },
    {
      "key": "borderRadius"
    },
    {
      "key": "text"
    }
  ],
  "dynamicHeight": "FIXED",
  "dynamicTriggerPathList": [
    {
      "key": "onClick"
    }
  ],
  "iconAlign": "left",
  "isDefaultClickDisabled": true,
  "isDisabled": false,
  "isLoading": false,
  "isVisible": true,
  "key": "61tr9rv49g",
  "leftColumn": 0,
  "minWidth": 120,
  "mobileBottomRow": 4,
  "mobileLeftColumn": 0,
  "mobileRightColumn": 12,
  "mobileTopRow": 0,
  "needsErrorInfo": false,
  "onClick": "{{navigateTo(currentItem.link, {}, 'NEW_WINDOW');}}",
  "parentColumnSpace": 14.0908203125,
  "parentId": "54ub53kz7n",
  "parentRowSpace": 10,
  "placement": "START",
  "recaptchaType": "V3",
  "renderMode": "CANVAS",
  "resetFormOnClick": false,
  "responsiveBehavior": "hug",
  "rightColumn": 48,
  "text": "{{currentItem.title}}",
  "topRow": 0,
  "type": "BUTTON_WIDGET",
  "version": 1,
  "widgetId": "qui702l7m4",
  "widgetName": "Button4"
}