{
  "gitSyncId": "674b5eaa29bd2146155b36c6_d5dc5e46-9e46-4afd-bc9c-490aec386dfd",
  "id": "Dashboard_LatLongWarning.getLatLongWarningList",
  "pluginId": "js-plugin",
  "pluginType": "JS",
  "unpublishedAction": {
    "actionConfiguration": {
      "encodeParamsToggle": true,
      "jsArguments": [],
      "paginationType": "NONE",
      "timeoutInMillisecond": 10000
    },
    "collectionId": "Dashboard_LatLongWarning",
    "confirmBeforeExecute": false,
    "datasource": {
      "isAutoGenerated": false,
      "name": "UNUSED_DATASOURCE",
      "pluginId": "js-plugin"
    },
    "dynamicBindingPathList": [
      {
        "key": "body"
      }
    ],
    "fullyQualifiedName": "LatLongWarning.getLatLongWarningList",
    "name": "getLatLongWarningList",
    "pageId": "Dashboard",
    "runBehaviour": "MANUAL",
    "userSetOnLoad": false
  }
}